{"assets":{"9AD9BB9C53F4CE5CA9A9B9AF1048F6F2":{"type":"texture","index":888,"assetRequest":{"type":"slide","state":"outgoing","slide":"43DEEA85-AC3B-4347-A856-2916B13D3724"},"url":{"web":"assets/9AD9BB9C53F4CE5CA9A9B9AF1048F6F2.svg"},"width":720,"height":540},"B3ABFEF9E3872B555819C0B5A1263217":{"type":"texture","index":889,"assetRequest":{"type":"slide","state":"incoming","slide":"676E69D9-C3F8-423D-8D6E-0944E69E2AA1"},"url":{"web":"assets/B3ABFEF9E3872B555819C0B5A1263217.svg"},"width":720,"height":540}},"events":[{"effects":[{"beginTime":0,"baseLayer":{"animations":[],"initialState":{"affineTransform":[1,0,0,1,0,0],"masksToBounds":false,"rotation":0,"scale":1,"position":{"pointX":360,"pointY":270},"width":720,"sublayerTransform":[1,0,0,0,0,1,0,0,0,0,1,0,0,0,0,1],"contentsRect":{"y":0,"x":0,"width":1,"height":1},"opacity":1,"edgeAntialiasingMask":251658240,"height":540,"hidden":false,"anchorPoint":{"pointX":0.5,"pointY":0.5}},"objectID":"0","layers":[{"animations":[],"initialState":{"affineTransform":[1,0,0,1,0,0],"masksToBounds":false,"rotation":0,"scale":1,"position":{"pointX":360,"pointY":270},"width":720,"sublayerTransform":[1,0,0,0,0,1,0,0,0,0,1,-0.0007001582493355197,0,0,0,1],"contentsRect":{"y":0,"x":0,"width":1,"height":1},"opacity":1,"edgeAntialiasingMask":251658240,"height":540,"hidden":false,"anchorPoint":{"pointX":0.5,"pointY":0.5}},"layers":[{"animations":[],"layers":[],"initialState":{"affineTransform":[1,0,0,1,0,0],"masksToBounds":false,"rotation":0,"scale":1,"position":{"pointX":360,"pointY":270},"width":720,"sublayerTransform":[1,0,0,0,0,1,0,0,0,0,1,0,0,0,0,1],"contentsRect":{"y":0,"x":0,"width":1,"height":1},"opacity":1,"edgeAntialiasingMask":0,"height":540,"hidden":false,"anchorPoint":{"pointX":0.5,"pointY":0.5}},"texture":"B3ABFEF9E3872B555819C0B5A1263217"},{"animations":[{"timeOffset":0,"from":{"scalar":false},"beginTime":0,"repeatCount":0,"fillMode":"both","property":"hidden","autoreverses":false,"duration":0.01,"to":{"scalar":true}}],"layers":[],"initialState":{"affineTransform":[1,0,0,1,0,0],"masksToBounds":false,"rotation":0,"scale":1,"position":{"pointX":360,"pointY":270},"width":720,"sublayerTransform":[1,0,0,0,0,1,0,0,0,0,1,0,0,0,0,1],"contentsRect":{"y":0,"x":0,"width":1,"height":1},"opacity":1,"edgeAntialiasingMask":0,"height":540,"hidden":false,"anchorPoint":{"pointX":0.5,"pointY":0.5}},"texture":"9AD9BB9C53F4CE5CA9A9B9AF1048F6F2"}]}]},"effects":[],"duration":0.01,"type":"transition","name":"none","objectID":"0"}],"automaticPlay":false,"hyperlinks":[],"accessibility":[{"text":"COS Software","targetRectangle":{"y":25.875,"x":184.6919999999999,"width":350.6160000000001,"height":67}},{"text":"(no attempt to be comprehensive)","targetRectangle":{"y":92.875,"x":178.1520000000001,"width":363.6959999999999,"height":29}},{"text":"Desktop","targetRectangle":{"y":195.25,"x":79.49424350261688,"width":96.798,"height":31}},{"text":"Agisoft Photoscan","targetRectangle":{"y":226.25,"x":114.4942435026169,"width":210.9899999999999,"height":60.53125}},{"text":"Pix4D","targetRectangle":{"y":286.78125,"x":114.4942435026169,"width":67.886,"height":60.53125}},{"text":"Simactive Correlator3D","targetRectangle":{"y":347.3125,"x":114.4942435026169,"width":148.33,"height":91.53125}},{"text":"Cloud","targetRectangle":{"y":193.8984313011169,"x":438.4226735830307,"width":69.34199999999998,"height":31}},{"text":"DroneMapper","targetRectangle":{"y":224.8984313011169,"x":473.4226735830307,"width":161.3299999999999,"height":60.53125}},{"text":"DroneDeploy","targetRectangle":{"y":285.4296813011169,"x":473.4226735830307,"width":152.672,"height":60.53125}},{"text":"DroneData","targetRectangle":{"y":345.9609313011169,"x":473.4226735830307,"width":125.242,"height":60.53125}},{"text":"Event38’s DDMS","targetRectangle":{"y":406.4921813011169,"x":473.4226735830307,"width":193.102,"height":60.53125}}],"baseLayer":{"animations":[],"initialState":{"affineTransform":[1,0,0,1,0,0],"masksToBounds":false,"rotation":0,"scale":1,"position":{"pointX":360,"pointY":270},"width":720,"sublayerTransform":[1,0,0,0,0,1,0,0,0,0,1,0,0,0,0,1],"contentsRect":{"y":0,"x":0,"width":1,"height":1},"opacity":1,"edgeAntialiasingMask":251658240,"height":540,"hidden":false,"anchorPoint":{"pointX":0.5,"pointY":0.5}},"objectID":"0","layers":[{"animations":[],"initialState":{"affineTransform":[1,0,0,1,0,0],"masksToBounds":false,"rotation":0,"scale":1,"position":{"pointX":360,"pointY":270},"width":720,"sublayerTransform":[1,0,0,0,0,1,0,0,0,0,1,-0.0007001582493355197,0,0,0,1],"contentsRect":{"y":0,"x":0,"width":1,"height":1},"opacity":1,"edgeAntialiasingMask":251658240,"height":540,"hidden":false,"anchorPoint":{"pointX":0.5,"pointY":0.5}},"layers":[{"animations":[],"layers":[],"initialState":{"affineTransform":[1,0,0,1,0,0],"masksToBounds":false,"rotation":0,"scale":1,"position":{"pointX":360,"pointY":270},"width":720,"sublayerTransform":[1,0,0,0,0,1,0,0,0,0,1,0,0,0,0,1],"contentsRect":{"y":0,"x":0,"width":1,"height":1},"opacity":1,"edgeAntialiasingMask":0,"height":540,"hidden":false,"anchorPoint":{"pointX":0.5,"pointY":0.5}},"texture":"9AD9BB9C53F4CE5CA9A9B9AF1048F6F2"}]}]}}]}